refy/__init__.py
refy/authors.py
refy/download.py
refy/infer.py
refy/input.py
refy/keywords.py
refy/recomend.py
refy/results.py
refy/settings.py
refy/suggestions.py
refy/utils.py
refy/web_utils.py
refy-1.0.0.8.dist-info/LICENSE
refy-1.0.0.8.dist-info/METADATA
refy-1.0.0.8.dist-info/WHEEL
refy-1.0.0.8.dist-info/entry_points.txt
refy-1.0.0.8.dist-info/top_level.txt
refy-1.0.0.8.dist-info/RECORD
