Metadata-Version: 2.1
Name: refy
Version: 1.0.0.8
Summary: A scientific papers recomendation tool.
Home-page: https://github.com/FedeClaudi/refy
Author: Federico Claudi
License: UNKNOWN
Platform: UNKNOWN
Classifier: Development Status :: 3 - Alpha
Classifier: Operating System :: POSIX :: Linux
Classifier: Operating System :: Microsoft :: Windows :: Windows 10
Classifier: Operating System :: MacOS :: MacOS X
Classifier: Programming Language :: Python
Classifier: Programming Language :: Python :: 3.6
Classifier: Programming Language :: Python :: 3.7
Classifier: Programming Language :: Python :: 3.8
Classifier: Intended Audience :: Developers
Classifier: Intended Audience :: Science/Research
Requires-Python: >3.6
Requires-Dist: pyinspect
Requires-Dist: pandas
Requires-Dist: loguru
Requires-Dist: requests
Requires-Dist: myterial
Requires-Dist: rich
Requires-Dist: bibtexparser
Requires-Dist: xmltodict
Requires-Dist: sklearn
Requires-Dist: gensim (==3.8.3)
Provides-Extra: dev
Requires-Dist: pytest ; extra == 'dev'
Requires-Dist: pytest-sugar ; extra == 'dev'
Requires-Dist: pytest-cov ; extra == 'dev'
Requires-Dist: coverage ; extra == 'dev'
